pymart/__init__.py
pymart/base.py
pymart/funcs.py
PyMart-0.0.1.dist-info/LICENCE
PyMart-0.0.1.dist-info/METADATA
PyMart-0.0.1.dist-info/WHEEL
PyMart-0.0.1.dist-info/top_level.txt
PyMart-0.0.1.dist-info/RECORD
