Metadata-Version: 2.1
Name: PyMart
Version: 0.0.1
Summary: Python based API wrapper around Ensembl's BioMart
Home-page: https://github.com/ivanp1994/PyMart.git
Author: Ivan Pokrovac
Author-email: ivan.pokrovac.fbf@gmail.com
License: MIT
Classifier: Development Status :: 3 - Alpha
Classifier: License :: OSI Approved :: MIT License
Classifier: Programming Language :: Python :: 3.8
Classifier: Programming Language :: Python :: 3 :: Only
Classifier: Intended Audience :: Science/Research
Requires-Python: >=3.8
License-File: LICENCE
Requires-Dist: requests (>=2.27.1)
Requires-Dist: pandas (>=1.4.1)
Provides-Extra: extra
Requires-Dist: flake8 (==3.9.2) ; extra == 'extra'
Requires-Dist: pytest (==6.2.5) ; extra == 'extra'
Requires-Dist: twine (==4.0.2) ; extra == 'extra'
Requires-Dist: wheel (==0.38.4) ; extra == 'extra'
